tradfri-0.0.5.data/scripts/tradfri
tradfricoap/__init__.py
tradfricoap/cli.py
tradfricoap/coapcmd_api.py
tradfricoap/colors.py
tradfricoap/config.py
tradfricoap/constants.py
tradfricoap/device.py
tradfricoap/device_info.py
tradfricoap/errors.py
tradfricoap/gateway.py
tradfricoap/pycoap_api.py
tradfricoap/request.py
tradfricoap/tradfri
tradfri-0.0.5.dist-info/METADATA
tradfri-0.0.5.dist-info/WHEEL
tradfri-0.0.5.dist-info/top_level.txt
tradfri-0.0.5.dist-info/RECORD
